nx2ipe/__init__.py
nx2ipe/nx2ipe.py
nx2ipe/static/__init__.py
nx2ipe/static/basic.xml
nx2ipe/static/settings.ini
nx2ipe-0.0.3.dist-info/METADATA
nx2ipe-0.0.3.dist-info/WHEEL
nx2ipe-0.0.3.dist-info/top_level.txt
nx2ipe-0.0.3.dist-info/RECORD
