Metadata-Version: 2.1
Name: nx2ipe
Version: 0.0.3
Summary: Convert networkX graphs into Ipe drawings 
Home-page: UNKNOWN
Author: Markus Wallinger
License: UNKNOWN
Platform: UNKNOWN
Classifier: Programming Language :: Python :: 3
Classifier: License :: OSI Approved :: MIT License
Classifier: Operating System :: OS Independent
Requires-Python: >=3.6
